bluetooth_mesh/application.py
bluetooth_mesh/apps.py
bluetooth_mesh/crypto.py
bluetooth_mesh/interfaces.py
bluetooth_mesh/mesh.py
bluetooth_mesh/models.py
bluetooth_mesh/provisioning.py
bluetooth_mesh/tokenring.py
bluetooth_mesh/utils.py
bluetooth_mesh/messages/generic/light.py
bluetooth_mesh-0.9.2.dist-info/licenses/LICENSE
bluetooth_mesh-0.9.2.dist-info/METADATA
bluetooth_mesh-0.9.2.dist-info/WHEEL
bluetooth_mesh-0.9.2.dist-info/top_level.txt
bluetooth_mesh-0.9.2.dist-info/RECORD
